{"timestamp":"2023-07-03T17:30:27.8024015Z","payload":{"InputEvents":0.0,"InputEventsPerSecond":0.0,"InputEventsBytes":0.0,"InputEventsBytesPerSecond":0.0,"InputEventsDegraded":0.0,"InputEventsDegradedPerSecond":0.0,"InputEventsEarly":0.0,"InputEventsEarlyPerSecond":0.0,"InputEventsLate":0.0,"InputEventsLatePerSecond":0.0,"InputEventsSources":1.0,"InputEventsSourcesBacklogged":2948.0,"InputEventsSourcesPerSecond":1.0,"InputEventsSerializerErrors":1.0,"InputEventsSerializerErrorsPerSecond":1.0,"InputWatermarkDelaySeconds":0.0}}
