{"timestamp":"2023-07-03T17:30:26.6839756Z","payload":{"InputEvents":0.0,"InputEventsBytes":0.0,"InputEventsEarly":0.0,"InputEventsLate":0.0,"InputEventsSourcesBacklogged":2948.0,"InputEventsSourcesPerSecond":1.0,"OutputEvents":0.0,"DeserializationErrors":1.0,"ConversionErrors":0.0,"Errors":0.0,"OutputWatermarkDelaySeconds":53890226.6839756}}
{"timestamp":"2023-07-03T17:30:27.7733279Z","payload":{"InputEvents":0.0,"InputEventsBytes":0.0,"InputEventsEarly":0.0,"InputEventsLate":0.0,"InputEventsSourcesBacklogged":2948.0,"InputEventsSourcesPerSecond":0.0,"OutputEvents":0.0,"DeserializationErrors":0.0,"ConversionErrors":0.0,"Errors":0.0,"OutputWatermarkDelaySeconds":53890227.7733279}}
